{"trailers":[{"id":"","lat":41.1481,"lng":-81.89782,"mtsn":"SHB7BLAG222161668","checkedIn":false,"pickedUp":false,"isNew":true},{"id":"265","lat":41.14732,"lng":-81.89691,"mtsn":"SHB7BLAG222161382","checkedIn":true,"pickedUp":false,"isNew":false},{"id":"267","lat":41.14715,"lng":-81.8969,"mtsn":"SHB7BLAG222161464","checkedIn":true,"pickedUp":false,"isNew":false},{"id":"28LG09","lat":41.14706,"lng":-81.89715,"mtsn":"GXL5ELAG200666243","checkedIn":true,"pickedUp":false,"isNew":false},{"id":"310464","lat":41.14735,"lng":-81.89751,"mtsn":"SHB7BLAG222162084","checkedIn":true,"pickedUp":false,"isNew":false},{"id":"33FB53","lat":41.14792,"lng":-81.89677,"mtsn":"SHB8AJBL240339514","checkedIn":true,"pickedUp":false,"isNew":false},{"id":"36717","lat":41.14731,"lng":-81.89783,"mtsn":"SVE5DJBL240206587","checkedIn":true,"pickedUp":false,"isNew":false},{"id":"44315","lat":41.14765,"lng":-81.89743,"mtsn":"SHB7CJBL232305535","checkedIn":true,"pickedUp":false,"isNew":false},{"id":"481702","lat":41.14789,"lng":-81.89735,"mtsn":"SHB8AJBL234933549","checkedIn":true,"pickedUp":false,"isNew":false},{"id":"481839LG","lat":41.14746,"lng":-81.89697,"mtsn":"SHB7BLAG222161029","checkedIn":true,"pickedUp":false,"isNew":false},{"id":"487270","lat":41.1473,"lng":-81.89777,"mtsn":"SHB81JBL233518668","checkedIn":true,"pickedUp":false,"isNew":false},{"id":"48A2202","lat":41.14852,"lng":-81.89722,"mtsn":"SHB8AJBL240238581","checkedIn":true,"pickedUp":false,"isNew":false},{"id":"48A2203","lat":41.14817,"lng":-81.89743,"mtsn":"SHB8AJBL240238534","checkedIn":true,"pickedUp":false,"isNew":false},{"id":"48A2331","lat":41.14818,"lng":-81.89719,"mtsn":"SHB8AJBL233922309","checkedIn":true,"pickedUp":false,"isNew":false},{"id":"48C2440","lat":41.14812,"lng":-81.89718,"mtsn":"SHB7CJBL232507548","checkedIn":true,"pickedUp":false,"isNew":false},{"id":"48C2448","lat":41.14795,"lng":-81.8971,"mtsn":"SHB8AJBL240238265","checkedIn":true,"pickedUp":false,"isNew":false},{"id":"48F923","lat":41.14888,"lng":-81.89668,"mtsn":"SHB8AJBL235136671","checkedIn":true,"pickedUp":false,"isNew":false},{"id":"494","lat":41.14751,"lng":-81.89787,"mtsn":"SHB7BLAG222161236","checkedIn":true,"pickedUp":false,"isNew":false},{"id":"5029","lat":41.14725,"lng":-81.89779,"mtsn":"SHB7BLAG222160966","checkedIn":true,"pickedUp":false,"isNew":false},{"id":"5088","lat":41.14702,"lng":-81.89715,"mtsn":"SHB7BLAG222161426","checkedIn":true,"pickedUp":false,"isNew":false},{"id":"5313020","lat":41.14763,"lng":-81.89652,"mtsn":"SHB81JBL233821736","checkedIn":true,"pickedUp":false,"isNew":false},{"id":"5314321","lat":41.14861,"lng":-81.89803,"mtsn":"SHB8AJBL233923169","checkedIn":true,"pickedUp":false,"isNew":false},{"id":"5315260","lat":41.14854,"lng":-81.89812,"mtsn":"SHB8AJBL233923017","checkedIn":true,"pickedUp":false,"isNew":false},{"id":"5317020","lat":41.14677,"lng":-81.89734,"mtsn":"SVE5CLAG223145750","checkedIn":true,"pickedUp":false,"isNew":false},{"id":"5317051","lat":41.14759,"lng":-81.89845,"mtsn":"SVE5DJBL240206676","checkedIn":true,"pickedUp":false,"isNew":false},{"id":"5317055","lat":41.14791,"lng":-81.89756,"mtsn":"SVE5DJBL240307055","checkedIn":true,"pickedUp":false,"isNew":false},{"id":"5317347","lat":41.14713,"lng":-81.89702,"mtsn":"SHB7CJBL234428290","checkedIn":true,"pickedUp":false,"isNew":false},{"id":"5317394","lat":41.14771,"lng":-81.8984,"mtsn":"SHB7CJBL232507039","checkedIn":true,"pickedUp":false,"isNew":false},{"id":"5317412","lat":41.14733,"lng":-81.89782,"mtsn":"SHB7CJBL234428271","checkedIn":true,"pickedUp":false,"isNew":false},{"id":"5317449","lat":41.14747,"lng":-81.89797,"mtsn":"SHB7CJBL233113441","checkedIn":true,"pickedUp":false,"isNew":false},{"id":"5317454","lat":41.14753,"lng":-81.89662,"mtsn":"SHB7CJBL240743555","checkedIn":true,"pickedUp":false,"isNew":false},{"id":"5317522","lat":41.14748,"lng":-81.89749,"mtsn":"SHB7BJBL232204679","checkedIn":true,"pickedUp":false,"isNew":false},{"id":"5317595","lat":41.14758,"lng":-81.89658,"mtsn":"SHB7CJBL240441585","checkedIn":true,"pickedUp":false,"isNew":false},{"id":"5317601","lat":41.14789,"lng":-81.89825,"mtsn":"SHB7BJBL225097250","checkedIn":false,"pickedUp":false,"isNew":true},{"id":"5317630","lat":41.14708,"lng":-81.89705,"mtsn":"SHB7CJBL232607904","checkedIn":true,"pickedUp":false,"isNew":false},{"id":"5317696","lat":41.14699,"lng":-81.89748,"mtsn":"SHB7CJBL233113520","checkedIn":true,"pickedUp":false,"isNew":false},{"id":"5317704","lat":41.14736,"lng":-81.89785,"mtsn":"SHB7CJBL233113447","checkedIn":true,"pickedUp":false,"isNew":false},{"id":"5317758","lat":41.14815,"lng":-81.8979,"mtsn":"SHB7CJBL240441582","checkedIn":true,"pickedUp":false,"isNew":false},{"id":"5317840","lat":41.14776,"lng":-81.8978,"mtsn":"SHB7CJBL233113451","checkedIn":true,"pickedUp":false,"isNew":false},{"id":"5317841","lat":41.14707,"lng":-81.89712,"mtsn":"SHB7CJBL233113424","checkedIn":true,"pickedUp":false,"isNew":false},{"id":"5317890","lat":41.14729,"lng":-81.89701,"mtsn":"SHB7CJBL240844287","checkedIn":true,"pickedUp":false,"isNew":false},{"id":"5317903","lat":41.14725,"lng":-81.89708,"mtsn":"SVE5DJBL232890472","checkedIn":true,"pickedUp":false,"isNew":false},{"id":"5317972","lat":41.14761,"lng":-81.89838,"mtsn":"SVE5DJBL234401080","checkedIn":true,"pickedUp":false,"isNew":false},{"id":"5318184","lat":41.14701,"lng":-81.89722,"mtsn":"SHB7BLAG222468711","checkedIn":true,"pickedUp":false,"isNew":false},{"id":"5319040","lat":41.14761,"lng":-81.89832,"mtsn":"SHB8AJBL234528903","checkedIn":false,"pickedUp":false,"isNew":true},{"id":"5319082","lat":41.14769,"lng":-81.89806,"mtsn":"SHB7BLAG222161542","checkedIn":true,"pickedUp":false,"isNew":false},{"id":"5319090","lat":41.14788,"lng":-81.8986,"mtsn":"SHB7BLAG222161588","checkedIn":true,"pickedUp":false,"isNew":false},{"id":"5320023","lat":41.14829,"lng":-81.89722,"mtsn":"SHB8AJBL234629699","checkedIn":false,"pickedUp":false,"isNew":true},{"id":"5320116","lat":41.14758,"lng":-81.89668,"mtsn":"SHB7BLAG222468592","checkedIn":true,"pickedUp":false,"isNew":false},{"id":"5321139","lat":41.14722,"lng":-81.89751,"mtsn":"SHB7BLAG222468670","checkedIn":true,"pickedUp":false,"isNew":false},{"id":"5321142","lat":41.147,"lng":-81.89724,"mtsn":"SHB7BLAG222468688","checkedIn":true,"pickedUp":false,"isNew":false},{"id":"5321144","lat":41.14835,"lng":-81.89801,"mtsn":"SHB7BLAG222468615","checkedIn":true,"pickedUp":false,"isNew":false},{"id":"5321147","lat":41.14853,"lng":-81.89835,"mtsn":"SHB7BLAG222468464","checkedIn":true,"pickedUp":false,"isNew":false},{"id":"5321149","lat":41.14812,"lng":-81.89749,"mtsn":"SHB7BLAG222468489","checkedIn":true,"pickedUp":false,"isNew":false},{"id":"5321156","lat":41.14712,"lng":-81.89734,"mtsn":"SHB7BLAG222468462","checkedIn":true,"pickedUp":false,"isNew":false},{"id":"5321504","lat":41.14727,"lng":-81.89686,"mtsn":"GXL5ELAG203105984","checkedIn":true,"pickedUp":false,"isNew":false},{"id":"5321644","lat":41.14778,"lng":-81.89804,"mtsn":"SHB7BLAG222161115","checkedIn":true,"pickedUp":false,"isNew":false},{"id":"532184","lat":41.14745,"lng":-81.89797,"mtsn":"SVE5DJBL233694886","checkedIn":true,"pickedUp":false,"isNew":false},{"id":"5321974","lat":41.1483,"lng":-81.89698,"mtsn":"SHB7BLAG222468585","checkedIn":true,"pickedUp":false,"isNew":false},{"id":"5321975","lat":41.14809,"lng":-81.89764,"mtsn":"SHB7BLAG222468677","checkedIn":true,"pickedUp":false,"isNew":false},{"id":"5321977","lat":41.14721,"lng":-81.89709,"mtsn":"SHB7BLAG222161394","checkedIn":true,"pickedUp":false,"isNew":false},{"id":"5321983","lat":41.14765,"lng":-81.89816,"mtsn":"SHB7BLAG222468725","checkedIn":true,"pickedUp":false,"isNew":false},{"id":"5322058","lat":41.14717,"lng":-81.89769,"mtsn":"GXL5HLAG204952810","checkedIn":false,"pickedUp":false,"isNew":true},{"id":"5322340","lat":41.14771,"lng":-81.89797,"mtsn":"GXL5HLAG204952884","checkedIn":false,"pickedUp":false,"isNew":true},{"id":"5322462","lat":41.14699,"lng":-81.89748,"mtsn":"GXL5HLAG210275302","checkedIn":false,"pickedUp":false,"isNew":true},{"id":"5322537","lat":41.14801,"lng":-81.89741,"mtsn":"GXL5HLAG210275239","checkedIn":true,"pickedUp":false,"isNew":false},{"id":"5322805","lat":41.14703,"lng":-81.89717,"mtsn":"SHB8AJBL234427924","checkedIn":true,"pickedUp":false,"isNew":false},{"id":"5322989","lat":41.14737,"lng":-81.89805,"mtsn":"GXL5JLAG213379681","checkedIn":false,"pickedUp":false,"isNew":true},{"id":"5323039","lat":41.14842,"lng":-81.89842,"mtsn":"SVE5CLAG221018260","checkedIn":true,"pickedUp":false,"isNew":false},{"id":"5323357","lat":41.14849,"lng":-81.89816,"mtsn":"SVE5CLAG222029074","checkedIn":true,"pickedUp":false,"isNew":false},{"id":"5324233","lat":41.14834,"lng":-81.89847,"mtsn":"SVE5CJBL231180814","checkedIn":true,"pickedUp":false,"isNew":false},{"id":"5324246","lat":41.14771,"lng":-81.89746,"mtsn":"SVE5CJBL231180831","checkedIn":true,"pickedUp":false,"isNew":false},{"id":"5324249","lat":41.14754,"lng":-81.89825,"mtsn":"SVE5CJBL231180791","checkedIn":false,"pickedUp":false,"isNew":true},{"id":"5327649","lat":41.14882,"lng":-81.89768,"mtsn":"SHB7BLAG222468549","checkedIn":false,"pickedUp":false,"isNew":true},{"id":"5327653","lat":41.1481,"lng":-81.89812,"mtsn":"SHB7BLAG222468472","checkedIn":false,"pickedUp":false,"isNew":true},{"id":"5327657","lat":41.14817,"lng":-81.89822,"mtsn":"SHB7BLAG222161595","checkedIn":false,"pickedUp":false,"isNew":true},{"id":"5327659","lat":41.1482,"lng":-81.89803,"mtsn":"SHB7BLAG222161661","checkedIn":false,"pickedUp":false,"isNew":true},{"id":"5340","lat":41.14755,"lng":-81.89666,"mtsn":"SHB7BLAG222161396","checkedIn":true,"pickedUp":false,"isNew":false},{"id":"535213","lat":41.14747,"lng":-81.89671,"mtsn":"SHB8AJBL240946659","checkedIn":true,"pickedUp":false,"isNew":false},{"id":"53710","lat":41.14729,"lng":-81.89674,"mtsn":"SHB7BLAG222161475","checkedIn":true,"pickedUp":false,"isNew":false},{"id":"53A1803","lat":41.14813,"lng":-81.89706,"mtsn":"SHB8AJBL241749143","checkedIn":true,"pickedUp":false,"isNew":false},{"id":"53C611","lat":41.14824,"lng":-81.89709,"mtsn":"SHB8AJBL241748822","checkedIn":true,"pickedUp":false,"isNew":false},{"id":"557305","lat":41.14685,"lng":-81.89726,"mtsn":"SHB8AJBL240542011","checkedIn":true,"pickedUp":false,"isNew":false},{"id":"557345","lat":41.14729,"lng":-81.89775,"mtsn":"SHB8AJBL240844775","checkedIn":true,"pickedUp":false,"isNew":false},{"id":"557346","lat":41.14775,"lng":-81.89777,"mtsn":"SHB8AJBL240844784","checkedIn":true,"pickedUp":false,"isNew":false},{"id":"557402","lat":41.14826,"lng":-81.89822,"mtsn":"SHB7CJBL232406202","checkedIn":true,"pickedUp":false,"isNew":false},{"id":"557403","lat":41.14721,"lng":-81.89778,"mtsn":"SHB8AJBL234730488","checkedIn":true,"pickedUp":false,"isNew":false},{"id":"557437","lat":41.14731,"lng":-81.89783,"mtsn":"SVE5CLAG222233179","checkedIn":true,"pickedUp":false,"isNew":false},{"id":"557482","lat":41.14773,"lng":-81.89835,"mtsn":"SHB8AJBL240844894","checkedIn":true,"pickedUp":false,"isNew":false},{"id":"558030","lat":41.14708,"lng":-81.89756,"mtsn":"SHB81JBL233417125","checkedIn":true,"pickedUp":false,"isNew":false},{"id":"561026","lat":41.1475,"lng":-81.89689,"mtsn":"SVE5CLAG223044084","checkedIn":true,"pickedUp":false,"isNew":false},{"id":"5616657","lat":41.14782,"lng":-81.89836,"mtsn":"SHB8AJBL241749194","checkedIn":true,"pickedUp":false,"isNew":false},{"id":"561701","lat":41.14748,"lng":-81.89829,"mtsn":"SHB8AJBL240946318","checkedIn":true,"pickedUp":false,"isNew":false},{"id":"5617151","lat":41.1471,"lng":-81.89718,"mtsn":"SVE5DJBL240307140","checkedIn":true,"pickedUp":false,"isNew":false},{"id":"561724","lat":41.14748,"lng":-81.89789,"mtsn":"SHB7BLAG221958026","checkedIn":true,"pickedUp":false,"isNew":false},{"id":"5617249","lat":41.14852,"lng":-81.89806,"mtsn":"SHB7CJBL234325793","checkedIn":true,"pickedUp":false,"isNew":false},{"id":"5617250","lat":41.14745,"lng":-81.89801,"mtsn":"SHB8AJBL233923264","checkedIn":true,"pickedUp":false,"isNew":false},{"id":"5617262","lat":41.14703,"lng":-81.89712,"mtsn":"SHB8AJBL234124508","checkedIn":true,"pickedUp":false,"isNew":false},{"id":"5617778","lat":41.14766,"lng":-81.89683,"mtsn":"SHB8AJBL240238065","checkedIn":true,"pickedUp":false,"isNew":false},{"id":"5617804","lat":41.14709,"lng":-81.89704,"mtsn":"SHB8AJBL234629450","checkedIn":true,"pickedUp":false,"isNew":false},{"id":"5617805","lat":41.14732,"lng":-81.89696,"mtsn":"SHB8AJBL234629440","checkedIn":true,"pickedUp":false,"isNew":false},{"id":"5617887","lat":41.14754,"lng":-81.89814,"mtsn":"SHB8AJBL234629416","checkedIn":true,"pickedUp":false,"isNew":false},{"id":"5618019","lat":41.14813,"lng":-81.89786,"mtsn":"SVE5DJBL232386991","checkedIn":true,"pickedUp":false,"isNew":false},{"id":"5618047","lat":41.14812,"lng":-81.8979,"mtsn":"SVE5DJBL232788838","checkedIn":true,"pickedUp":false,"isNew":false},{"id":"5619017","lat":41.14756,"lng":-81.89831,"mtsn":"GXL7LLAG222013581","checkedIn":true,"pickedUp":false,"isNew":false},{"id":"5620408","lat":41.1486,"lng":-81.89824,"mtsn":"SHB81JBL233821288","checkedIn":true,"pickedUp":false,"isNew":false},{"id":"5620426","lat":41.14713,"lng":-81.89704,"mtsn":"SHB7BJBL232103327","checkedIn":true,"pickedUp":false,"isNew":false},{"id":"5620507","lat":41.14791,"lng":-81.89747,"mtsn":"SVE5CJBL232185526","checkedIn":true,"pickedUp":false,"isNew":false},{"id":"5620515","lat":41.1489,"lng":-81.89793,"mtsn":"SHB8AJBL241849961","checkedIn":false,"pickedUp":false,"isNew":true},{"id":"5620587","lat":41.14855,"lng":-81.89838,"mtsn":"SHB7BLAG222467882","checkedIn":true,"pickedUp":false,"isNew":false},{"id":"5621006","lat":41.14741,"lng":-81.89771,"mtsn":"SHB7BJBL231694129","checkedIn":true,"pickedUp":false,"isNew":false},{"id":"5622122","lat":41.14749,"lng":-81.89677,"mtsn":"GXL5JLAG211428887","checkedIn":false,"pickedUp":false,"isNew":true},{"id":"5622134","lat":41.1473,"lng":-81.89688,"mtsn":"GXL5JLAG211844505","checkedIn":true,"pickedUp":false,"isNew":false},{"id":"5622154","lat":41.14746,"lng":-81.89799,"mtsn":"SVE5BLAG214004981","checkedIn":false,"pickedUp":false,"isNew":true},{"id":"5622420","lat":41.14746,"lng":-81.89677,"mtsn":"GXL5JLAG211532069","checkedIn":false,"pickedUp":false,"isNew":true},{"id":"5622568","lat":41.14717,"lng":-81.89706,"mtsn":"SHB8AJBL235034384","checkedIn":false,"pickedUp":false,"isNew":true},{"id":"5622892","lat":41.14789,"lng":-81.89772,"mtsn":"GXL5JLAG213379688","checkedIn":true,"pickedUp":false,"isNew":false},{"id":"5623187","lat":41.14848,"lng":-81.89838,"mtsn":"SHB7BLAG222468617","checkedIn":true,"pickedUp":false,"isNew":false},{"id":"5623797","lat":41.14684,"lng":-81.89729,"mtsn":"SVE5CLAG223044122","checkedIn":true,"pickedUp":false,"isNew":false},{"id":"5624018","lat":41.14787,"lng":-81.8979,"mtsn":"SVE5CLAG222539538","checkedIn":false,"pickedUp":false,"isNew":true},{"id":"5624180","lat":41.14827,"lng":-81.89815,"mtsn":"SHB8AJBL241748831","checkedIn":true,"pickedUp":false,"isNew":false},{"id":"5624589","lat":41.14703,"lng":-81.89713,"mtsn":"SVE5CJBL230877406","checkedIn":true,"pickedUp":false,"isNew":false},{"id":"5624779","lat":41.14797,"lng":-81.89726,"mtsn":"SVE5CLAG223852940","checkedIn":true,"pickedUp":false,"isNew":false},{"id":"5624818","lat":41.147,"lng":-81.89759,"mtsn":"SVE5CLAG223852955","checkedIn":false,"pickedUp":false,"isNew":true},{"id":"5624910","lat":41.14709,"lng":-81.8971,"mtsn":"SVE5DJBL232788935","checkedIn":true,"pickedUp":false,"isNew":false},{"id":"5624912","lat":41.14712,"lng":-81.89752,"mtsn":"SVE5DJBL232788910","checkedIn":false,"pickedUp":false,"isNew":true},{"id":"5624930","lat":41.14783,"lng":-81.8977,"mtsn":"SVE5CLAG223750116","checkedIn":true,"pickedUp":false,"isNew":false},{"id":"563626","lat":41.14829,"lng":-81.89825,"mtsn":"SVE5DJBL232386577","checkedIn":true,"pickedUp":false,"isNew":false},{"id":"564596","lat":41.14735,"lng":-81.89672,"mtsn":"SHB81JBL233314941","checkedIn":true,"pickedUp":false,"isNew":false},{"id":"566399","lat":41.14783,"lng":-81.89814,"mtsn":"SVE5DJBL232588314","checkedIn":true,"pickedUp":false,"isNew":true},{"id":"566511","lat":41.14759,"lng":-81.89819,"mtsn":"SVE5CLAG222233017","checkedIn":true,"pickedUp":false,"isNew":false},{"id":"567724","lat":41.14751,"lng":-81.89799,"mtsn":"SVE5CLAG221626935","checkedIn":true,"pickedUp":false,"isNew":false},{"id":"568333","lat":41.14855,"lng":-81.89835,"mtsn":"SVE5CLAG223446677","checkedIn":true,"pickedUp":false,"isNew":false},{"id":"568654","lat":41.14775,"lng":-81.89847,"mtsn":"GXL5ELAG202797383","checkedIn":true,"pickedUp":false,"isNew":false},{"id":"568827","lat":41.14753,"lng":-81.89693,"mtsn":"SVE5CLAG222435071","checkedIn":true,"pickedUp":false,"isNew":false},{"id":"569002","lat":41.14752,"lng":-81.89693,"mtsn":"GXL1ASPD182132885","checkedIn":true,"pickedUp":false,"isNew":false},{"id":"569059","lat":41.14849,"lng":-81.89771,"mtsn":"SHB7BJBL231801572","checkedIn":true,"pickedUp":false,"isNew":false},{"id":"581302","lat":41.14748,"lng":-81.8978,"mtsn":"SVE5CLAG221523202","checkedIn":true,"pickedUp":false,"isNew":false},{"id":"581862","lat":41.14743,"lng":-81.89799,"mtsn":"SHB8AJBL234427943","checkedIn":true,"pickedUp":false,"isNew":false},{"id":"581959","lat":41.14769,"lng":-81.89758,"mtsn":"SHB8AJBL240338898","checkedIn":true,"pickedUp":false,"isNew":false},{"id":"5822014","lat":41.14705,"lng":-81.89737,"mtsn":"SHB7BLAG222161023","checkedIn":true,"pickedUp":false,"isNew":false},{"id":"587706LG","lat":41.1467,"lng":-81.89729,"mtsn":"GXL5HLAG204746107","checkedIn":true,"pickedUp":false,"isNew":false},{"id":"6039","lat":41.14759,"lng":-81.89655,"mtsn":"SHB7BLAG222161447","checkedIn":true,"pickedUp":false,"isNew":false},{"id":"6096","lat":41.14759,"lng":-81.8981,"mtsn":"SHB7BLAG222161238","checkedIn":true,"pickedUp":false,"isNew":false},{"id":"6100","lat":41.1475,"lng":-81.89793,"mtsn":"SHB7BLAG222161487","checkedIn":true,"pickedUp":false,"isNew":false},{"id":"6382","lat":41.14762,"lng":-81.89754,"mtsn":"SHB7BLAG222161482","checkedIn":true,"pickedUp":false,"isNew":false},{"id":"6383","lat":41.14778,"lng":-81.89733,"mtsn":"SHB7BLAG222162070","checkedIn":true,"pickedUp":false,"isNew":false},{"id":"6826","lat":41.14731,"lng":-81.89679,"mtsn":"SHB7BLAG222161413","checkedIn":true,"pickedUp":false,"isNew":false},{"id":"78902","lat":41.14773,"lng":-81.897,"mtsn":"SVE5DJBL234400177","checkedIn":true,"pickedUp":false,"isNew":false},{"id":"97517","lat":41.14805,"lng":-81.89761,"mtsn":"SVE5DJBL240206628","checkedIn":true,"pickedUp":false,"isNew":false},{"id":"MT53166","lat":41.14749,"lng":-81.89655,"mtsn":"SHB8AJBL233922246","checkedIn":true,"pickedUp":false,"isNew":false},{"id":"MTRZ309166","lat":41.14764,"lng":-81.89821,"mtsn":"SHB8AJBL235136491","checkedIn":true,"pickedUp":false,"isNew":false},{"id":"MTRZ317038","lat":41.14884,"lng":-81.89778,"mtsn":"SVE5DJBL240307105","checkedIn":false,"pickedUp":false,"isNew":true},{"id":"MTRZ317177","lat":41.14796,"lng":-81.89786,"mtsn":"SHB8AJBL233923123","checkedIn":false,"pickedUp":false,"isNew":true},{"id":"MTRZ317494","lat":41.14694,"lng":-81.89722,"mtsn":"SHB7CJBL232305581","checkedIn":true,"pickedUp":false,"isNew":false},{"id":"MTRZ317894","lat":41.148,"lng":-81.89828,"mtsn":"SHB81JBL233518587","checkedIn":true,"pickedUp":false,"isNew":false},{"id":"MTRZ321351","lat":41.14829,"lng":-81.89745,"mtsn":"GXL5ELAG203107109","checkedIn":false,"pickedUp":false,"isNew":true},{"id":"MTRZ322594","lat":41.14901,"lng":-81.89791,"mtsn":"GXL5JLAG210694986","checkedIn":false,"pickedUp":false,"isNew":true},{"id":"MTRZ322645","lat":41.14791,"lng":-81.89725,"mtsn":"GXL5JLAG210694845","checkedIn":true,"pickedUp":false,"isNew":false},{"id":"MTRZ323240","lat":41.14721,"lng":-81.89777,"mtsn":"SVE5CLAG222027996","checkedIn":true,"pickedUp":false,"isNew":false},{"id":"MTRZ450045","lat":41.14809,"lng":-81.89771,"mtsn":"SHB81JBL233417185","checkedIn":true,"pickedUp":false,"isNew":false},{"id":"MTRZ557102","lat":41.1471,"lng":-81.89719,"mtsn":"SVE5BLAG214407115","checkedIn":true,"pickedUp":false,"isNew":false},{"id":"MTRZ557394","lat":41.14736,"lng":-81.89677,"mtsn":"SHB8AJBL240844946","checkedIn":true,"pickedUp":false,"isNew":false},{"id":"MTRZ560701","lat":41.14758,"lng":-81.89814,"mtsn":"SHB8AJBL234629316","checkedIn":true,"pickedUp":false,"isNew":false},{"id":"MTRZ566572","lat":41.14771,"lng":-81.89798,"mtsn":"SVE5DJBL232688693","checkedIn":true,"pickedUp":false,"isNew":false},{"id":"MTRZ567359","lat":41.14795,"lng":-81.89833,"mtsn":"SVE5DJBL233694719","checkedIn":true,"pickedUp":false,"isNew":false},{"id":"MTRZ568582","lat":41.14742,"lng":-81.89684,"mtsn":"SHB7BLAG224083059","checkedIn":true,"pickedUp":false,"isNew":false},{"id":"MTRZ568602","lat":41.14679,"lng":-81.89731,"mtsn":"SVE5CLAG221524714","checkedIn":false,"pickedUp":false,"isNew":true},{"id":"MTRZ568863","lat":41.14785,"lng":-81.89826,"mtsn":"SHB7BLAG223578047","checkedIn":true,"pickedUp":false,"isNew":false},{"id":"MTRZ587711","lat":41.14809,"lng":-81.89831,"mtsn":"SHB8AJBL234931928","checkedIn":false,"pickedUp":false,"isNew":true},{"id":"MTRZ617050","lat":41.14812,"lng":-81.89836,"mtsn":"SHB7CJBL240743530","checkedIn":true,"pickedUp":false,"isNew":false},{"id":"MTRZ617081","lat":41.14698,"lng":-81.89723,"mtsn":"SVE5DJBL232891174","checkedIn":true,"pickedUp":false,"isNew":false},{"id":"MTRZ621416","lat":41.14692,"lng":-81.89758,"mtsn":"GXL5ELAG202491223","checkedIn":true,"pickedUp":false,"isNew":false},{"id":"MTRZ622038","lat":41.14857,"lng":-81.89841,"mtsn":"GXL5JLAG211529390","checkedIn":true,"pickedUp":false,"isNew":false},{"id":"MTRZ622545","lat":41.14801,"lng":-81.8983,"mtsn":"GXL5JLAG211532221","checkedIn":false,"pickedUp":false,"isNew":true},{"id":"MTRZ623160","lat":41.14816,"lng":-81.89845,"mtsn":"SVE5DJBL240206625","checkedIn":false,"pickedUp":false,"isNew":true},{"id":"MTRZ624282","lat":41.14844,"lng":-81.89738,"mtsn":"SVE5CLAG223854516","checkedIn":false,"pickedUp":false,"isNew":true},{"id":"MTRZ625034","lat":41.14773,"lng":-81.89761,"mtsn":"SHB7BJBL231902128","checkedIn":true,"pickedUp":false,"isNew":false},{"id":"MTRZ625094","lat":41.14766,"lng":-81.89654,"mtsn":"SHB7BJBL231902144","checkedIn":false,"pickedUp":false,"isNew":true},{"id":"MTRZ625129","lat":41.14696,"lng":-81.89742,"mtsn":"SHB7BJBL231902035","checkedIn":true,"pickedUp":false,"isNew":false},{"id":"MTRZ625295","lat":41.14752,"lng":-81.89659,"mtsn":"SHB7BJBL231902107","checkedIn":false,"pickedUp":false,"isNew":true},{"id":"T2129","lat":41.14833,"lng":-81.89743,"mtsn":"SHB8AJBL240238525","checkedIn":true,"pickedUp":false,"isNew":false},{"id":"T2754","lat":41.14824,"lng":-81.89708,"mtsn":"SHB8AJBL235136912","checkedIn":true,"pickedUp":false,"isNew":false},{"id":"T3343","lat":41.14832,"lng":-81.89749,"mtsn":"SHB8AJBL235136914","checkedIn":true,"pickedUp":false,"isNew":false},{"id":"T4352","lat":41.14725,"lng":-81.89635,"mtsn":"SHB7BLAG222161024","checkedIn":true,"pickedUp":false,"isNew":false}],"timestamp":"2026-03-25T07:31:15.8281075Z","lastUpdateSource":"skybitz-api"}